mesh2vec/__init__.py
mesh2vec/helpers.py
mesh2vec/mesh2vec_base.py
mesh2vec/mesh2vec_cae.py
mesh2vec/mesh2vec_exceptions.py
mesh2vec/mesh_features.py
mesh2vec/py.typed
mesh2vec/templates/ansa.py
mesh2vec-1.3.2.dist-info/METADATA
mesh2vec-1.3.2.dist-info/WHEEL
mesh2vec-1.3.2.dist-info/licenses/LICENSE
mesh2vec-1.3.2.dist-info/RECORD
