Metadata-Version: 2.4
Name: mesh2vec
Version: 1.3.2
Summary: Aggregate feature vectors on CAE meshes.
License-Expression: MIT
License-File: LICENSE
Author: Renumics GmbH
Author-email: info@renumics.com
Requires-Python: >=3.11,<4.0
Classifier: Programming Language :: Python :: 3
Classifier: Programming Language :: Python :: 3.11
Classifier: Programming Language :: Python :: 3.12
Classifier: Programming Language :: Python :: 3.13
Classifier: Programming Language :: Python :: 3.14
Requires-Dist: joblib (>=1.5.0,<2.0.0)
Requires-Dist: lasso-python (>=2.0.4,<3.0.0)
Requires-Dist: loguru (>=0.7.0,<1.0.0)
Requires-Dist: networkx (>=3.5.0,<4.0.0)
Requires-Dist: numpy (>=2.2.2,<3.0.0)
Requires-Dist: pandas (>=2.3.0,<3.0.0)
Requires-Dist: plotly (>=5.24.0,<6.0.0)
Requires-Dist: scipy (>=1.15.0,<2.0.0)
Requires-Dist: trimesh (>=4.6.0,<5.0.0)
